MANIFEST.in
README.txt
setup.cfg
setup.py
collective/.DS_Store
collective/__init__.py
collective.multifilesextender.egg-info/PKG-INFO
collective.multifilesextender.egg-info/SOURCES.txt
collective.multifilesextender.egg-info/dependency_links.txt
collective.multifilesextender.egg-info/entry_points.txt
collective.multifilesextender.egg-info/namespace_packages.txt
collective.multifilesextender.egg-info/not-zip-safe
collective.multifilesextender.egg-info/requires.txt
collective.multifilesextender.egg-info/top_level.txt
collective/multifilesextender/.DS_Store
collective/multifilesextender/__init__.py
collective/multifilesextender/configure.zcml
collective/multifilesextender/extender.py
collective/multifilesextender/interfaces.py
collective/multifilesextender/tests.py
collective/multifilesextender/usei18ndude.sh
collective/multifilesextender/viewlet.pt
collective/multifilesextender/viewlet.py
collective/multifilesextender/locales/.DS_Store
collective/multifilesextender/locales/collective.multifilesextender.pot
collective/multifilesextender/locales/manual.pot
collective/multifilesextender/locales/cs/LC_MESSAGES/collective.multifilesextender.mo
collective/multifilesextender/locales/cs/LC_MESSAGES/collective.multifilesextender.po
collective/multifilesextender/locales/da/.DS_Store
collective/multifilesextender/locales/da/LC_MESSAGES/collective.multifilesextender.mo
collective/multifilesextender/locales/da/LC_MESSAGES/collective.multifilesextender.po
collective/multifilesextender/locales/en/LC_MESSAGES/collective.multifilesextender.mo
collective/multifilesextender/locales/en/LC_MESSAGES/collective.multifilesextender.po
collective/multifilesextender/profiles/default/browserlayer.xml
collective/multifilesextender/profiles/default/metadata.xml
docs/HISTORY.txt
docs/INSTALL.txt
docs/LICENSE.GPL
docs/LICENSE.txt