Metadata-Version: 1.0
Name: collective.multifilesextender
Version: 1.1
Summary: This package extends any AT content type by a multi file field
Home-page: http://pypi.python.org/pypi/collective.multifilesextender
Author: Matous Hora
Author-email: matous.hora@dms4u.cz
License: GPL
Keywords: multifile,schemaextender,attachments
Platform: UNKNOWN
Classifier: Framework :: Plone
Classifier: Programming Language :: Python
Classifier: Topic :: Software Development :: Libraries :: Python Modules
